optimization_problem_inspector/__about__.py
optimization_problem_inspector/__init__.py
optimization_problem_inspector/app.py
optimization_problem_inspector/app_strings.py
optimization_problem_inspector/coco_interface.py
optimization_problem_inspector/config.py
optimization_problem_inspector/errors.py
optimization_problem_inspector/features.py
optimization_problem_inspector/logger.py
optimization_problem_inspector/models.py
optimization_problem_inspector/problem.py
optimization_problem_inspector/sampling.py
optimization_problem_inspector/serialization.py
optimization_problem_inspector/assets/gui-help.md
optimization_problem_inspector/assets/typography.css
optimization_problem_inspector-0.6.1.dist-info/METADATA
optimization_problem_inspector-0.6.1.dist-info/WHEEL
optimization_problem_inspector-0.6.1.dist-info/entry_points.txt
optimization_problem_inspector-0.6.1.dist-info/licenses/LICENSE.txt
optimization_problem_inspector-0.6.1.dist-info/RECORD
