Metadata-Version: 2.3
Name: optimization-problem-inspector
Version: 0.6.1
Summary: A tool for analysis of industrial optimization problems and their solutions
Project-URL: Documentation, https://github.com/unknown/optimization-problem-inspector#readme
Project-URL: Issues, https://github.com/unknown/optimization-problem-inspector/issues
Project-URL: Source, https://github.com/unknown/optimization-problem-inspector
Author-email: Jernej Zupančič <88.jernej@gmail.com>
License-Expression: MIT
License-File: LICENSE.txt
Classifier: Development Status :: 4 - Beta
Classifier: Programming Language :: Python
Classifier: Programming Language :: Python :: 3.10
Classifier: Programming Language :: Python :: 3.11
Classifier: Programming Language :: Python :: Implementation :: CPython
Requires-Python: >=3.10
Requires-Dist: coco-experiment
Requires-Dist: cython
Requires-Dist: dash
Requires-Dist: dash-bootstrap-components
Requires-Dist: loguru
Requires-Dist: pandas
Requires-Dist: pflacco
Requires-Dist: pydantic<2
Requires-Dist: pygmo
Requires-Dist: pyyaml
Requires-Dist: scipy
